ascend_community/__init__.py
ascend_community/cli.py
ascend_community/lib/decomplect.py
ascend_community/lib/dev.py
ascend_community-0.1.0.dist-info/WHEEL
ascend_community-0.1.0.dist-info/entry_points.txt
ascend_community-0.1.0.dist-info/METADATA
ascend_community-0.1.0.dist-info/RECORD
