Metadata-Version: 2.3
Name: ascend-community
Version: 0.1.0
Summary: Ascend Community code
Author: Cody, Shifra
Author-email: Cody <cody.peterson@ascend.io>, Shifra <shifra@ascend.io>
Requires-Dist: ibis-framework[bigquery,duckdb,postgres,snowflake,sqlite]>=10.6.0
Requires-Dist: pandas>=2.2.3
Requires-Dist: plotly>=6.3.0
Requires-Dist: polars>=1.32.2
Requires-Dist: pyyaml>=6.0.2
Requires-Dist: rich>=14.1.0
Requires-Dist: typer>=0.16.0
Requires-Python: >=3.13
